MANIFEST.in
README.md
openapi_version
setup.py
dingman_openapi_server.egg-info/PKG-INFO
dingman_openapi_server.egg-info/SOURCES.txt
dingman_openapi_server.egg-info/dependency_links.txt
dingman_openapi_server.egg-info/requires.txt
dingman_openapi_server.egg-info/top_level.txt
openapi_server/__init__.py
openapi_server/__main__.py
openapi_server/encoder.py
openapi_server/typing_utils.py
openapi_server/util.py
openapi_server/controllers/__init__.py
openapi_server/controllers/deploy_details_controller.py
openapi_server/controllers/deploy_resources_controller.py
openapi_server/controllers/security_controller_.py
openapi_server/models/__init__.py
openapi_server/models/affinity.py
openapi_server/models/base_model_.py
openapi_server/models/config.py
openapi_server/models/config_templates.py
openapi_server/models/container.py
openapi_server/models/container_life_cycle.py
openapi_server/models/container_port.py
openapi_server/models/container_sec_context.py
openapi_server/models/container_sec_context_capabilities.py
openapi_server/models/custom_manifest.py
openapi_server/models/deploy_platform_resource.py
openapi_server/models/deploy_resources.py
openapi_server/models/deployment_detail.py
openapi_server/models/deployment_detail_last_deployment.py
openapi_server/models/deployment_resource_status.py
openapi_server/models/deployment_resource_status_status.py
openapi_server/models/dingman_error.py
openapi_server/models/dingman_response.py
openapi_server/models/endpoint.py
openapi_server/models/env_from_source.py
openapi_server/models/env_var.py
openapi_server/models/env_var_source.py
openapi_server/models/env_var_source_config_map_key_ref.py
openapi_server/models/env_var_source_secret_key_ref.py
openapi_server/models/http_get.py
openapi_server/models/http_ingress_path.py
openapi_server/models/ingress.py
openapi_server/models/ingress_backend.py
openapi_server/models/ingress_backend_service.py
openapi_server/models/ingress_rule.py
openapi_server/models/ingress_tls.py
openapi_server/models/life_cycle_handler.py
openapi_server/models/node_affinity.py
openapi_server/models/node_selector.py
openapi_server/models/node_selector_term.py
openapi_server/models/object_field_selector.py
